<?xml version="1.0" encoding="UTF-8"?>
<endpoint name="WSO2APC_RECHARGE_EP" xmlns="http://ws.apache.org/ns/synapse">
    <http method="post" uri-template="http://wso2-1-rev-apc-svc-ci-mi:8290/apcrefill/TopUp/refill">
        <timeout>
            <duration>15000</duration>
            <responseAction>fault</responseAction>
        </timeout>
        <suspendOnFailure>
            <initialDuration>-1</initialDuration>
            <progressionFactor>1.0</progressionFactor>
        </suspendOnFailure>
        <markForSuspension>
            <retriesBeforeSuspension>0</retriesBeforeSuspension>
        </markForSuspension>
    </http>
</endpoint>
